PyErr.py
PyErrs-0.3.0.dist-info/LICENSE
PyErrs-0.3.0.dist-info/METADATA
PyErrs-0.3.0.dist-info/WHEEL
PyErrs-0.3.0.dist-info/top_level.txt
PyErrs-0.3.0.dist-info/RECORD
