Metadata-Version: 2.1
Name: PyErrs
Version: 0.3.0
Summary: More Python Exceptions
Home-page: https://github.com/usr8820/PyErrs/
Author: Frank Lin
Author-email: W_126mail@126.com
License: UNKNOWN
Platform: UNKNOWN
Classifier: Programming Language :: Python :: 3
Classifier: License :: OSI Approved :: MIT License
Classifier: Operating System :: OS Independent
Requires-Python: >=3.4
